{
  "version": 1,
  "updatedAt": "2026-05-02T16:01:52.870+05:30",
  "lastLink": "https://www.bleepingcomputer.com/news/security/story-retracted/",
  "lastId": "a41wk30000",
  "lastFilePath": "bleepingcomp/pages/2026/05/01/story-retracted.md",
  "items": [
    {
      "id": "a41wk30000",
      "link": "https://www.bleepingcomputer.com/news/security/story-retracted/",
      "filePath": "bleepingcomp/pages/2026/05/01/story-retracted.md",
      "committedAt": "2026-05-02T16:01:52.870+05:30",
      "title": "Story retracted"
    }
  ]
}